old/lib/checked/DelayOr.v
module DelayOr (input a, b, output out);
	parameter delay = 10;
	or #delay or_gate (out, a, b);
endmodule

old/lib/checked/DelayAnd.v
module DelayAnd (input a, b, output out);
	parameter delay = 10;
	and #delay and_gate (out, a, b);
endmodule

old/lib/checked/DelayXor.v
module DelayXor (input a, b, output out);
	parameter delay = 10;
	xor #delay xor_gate (out, a, b);
endmodule

old/lib/checked/half_adder.v
module half_adder(
	input a, b,
	output sum,carry
);
    DelayXor xor1(.a(a), .b(b), .out(sum));
    DelayAnd and1(.a(a), .b(b), .out(carry));
endmodule

old/lib/checked/full_adder.v
module full_adder (
    input a, b, cin,
    output sum, cout
);
    wire sum_half, carry_half, carry_half_2;

    half_adder half_adder1 (.a(a), .b(b), .sum(sum_half), .carry(carry_half));
    half_adder half_adder2 (.a(sum_half), .b(cin), .sum(sum), .carry(carry_half_2));
    DelayOr or1(.a(carry_half), .b(carry_half_2), .out(cout));
endmodule

old/lib/checked/adder.v
module adder #(
	parameter WIDTH = 1
) (
	input [WIDTH-1:0] a, b,
	input cin,
	output [WIDTH-1:0] sum,
	output cout
);
	wire [WIDTH-2:0] carry_line;
	full_adder full_adder1 [WIDTH-1:0] (
		.a(a), .b(b), .cin({carry_line, cin}), .sum(sum), .cout({cout, carry_line})
	);
	
endmodule

old/lib/testbench/adder_tb.v
`timescale 1ns / 1ns

module adder_tb;
	parameter WIDTH = 4;
	parameter DELAY = 2000;
	
	reg [WIDTH-1:0] a, b;
	reg cin;
	wire [WIDTH-1:0] sum;
	wire cout;
	
	adder #(.WIDTH(WIDTH)) dut (
		.a(a),
		.b(b),
		.cin(cin),
		.sum(sum),
		.cout(cout)
	);
	
	initial begin
		// Dump VCD file
		$dumpfile("testbench/adder_tb.vcd");
		$dumpvars(0, adder_tb);

		// Test case 1
		a = 4'b0000;
		b = 4'b0000;
		cin = 0;
		#DELAY;
		$display("a = %b, b = %b, cin = %b, sum = %b, cout = %b", a, b, cin, sum, cout);
		
		// Test case 2
		a = 4'b1010;
		b = 4'b0110;
		cin = 1;
		#DELAY;
		$display("a = %b, b = %b, cin = %b, sum = %b, cout = %b", a, b, cin, sum, cout);
		
		// Add more test cases here...
		
		// Test case 3
		a = 4'b1111;
		b = 4'b0001;
		cin = 0;
		#DELAY;

		
		// Test case 4
		a = 4'b0101;
		b = 4'b0011;
		cin = 1;
		#DELAY;

		$display("a = %b, b = %b, cin = %b, sum = %b, cout = %b", a, b, cin, sum, cout);

		// Test case 5
		a = 4'b1100;
		b = 4'b1010;
		cin = 0;
		#DELAY;

		$display("a = %b, b = %b, cin = %b, sum = %b, cout = %b", a, b, cin, sum, cout);

		// Test case 6
		a = 4'b0111;
		b = 4'b1001;
		cin = 1;
		#DELAY;

		$display("a = %b, b = %b, cin = %b, sum = %b, cout = %b", a, b, cin, sum, cout);
		


		$finish;
	end
endmodule

// current directory: 21011056/Q1/lib
// command: iverilog -o testbench/adder_tb.vvp -y ../lib testbench/adder_tb.v
// command: vvp testbench/adder_tb.vvp

old/lib/testbench/adder_tb.vcd
$date
	Mon Apr 29 22:29:23 2024
$end
$version
	Icarus Verilog
$end
$timescale
	1ns
$end
$scope module adder_tb $end
$var wire 4 ! sum [3:0] $end
$var wire 1 " cout $end
$var parameter 32 # DELAY $end
$var parameter 32 $ WIDTH $end
$var reg 4 % a [3:0] $end
$var reg 4 & b [3:0] $end
$var reg 1 ' cin $end
$scope module dut $end
$var wire 4 ( a [3:0] $end
$var wire 4 ) b [3:0] $end
$var wire 1 ' cin $end
$var wire 4 * sum [3:0] $end
$var wire 1 " cout $end
$var wire 3 + carry_line [2:0] $end
$var parameter 32 , WIDTH $end
$scope module full_adder1[0] $end
$var wire 1 - a $end
$var wire 1 . b $end
$var wire 1 / cin $end
$var wire 1 0 sum_half $end
$var wire 1 1 sum $end
$var wire 1 2 cout $end
$var wire 1 3 carry_half_2 $end
$var wire 1 4 carry_half $end
$scope module half_adder1 $end
$var wire 1 - a $end
$var wire 1 . b $end
$var wire 1 0 sum $end
$var wire 1 4 carry $end
$scope module and1 $end
$var wire 1 - a $end
$var wire 1 . b $end
$var wire 1 4 out $end
$var parameter 32 5 delay $end
$upscope $end
$scope module xor1 $end
$var wire 1 - a $end
$var wire 1 . b $end
$var wire 1 0 out $end
$var parameter 32 6 delay $end
$upscope $end
$upscope $end
$scope module half_adder2 $end
$var wire 1 0 a $end
$var wire 1 / b $end
$var wire 1 1 sum $end
$var wire 1 3 carry $end
$scope module and1 $end
$var wire 1 0 a $end
$var wire 1 / b $end
$var wire 1 3 out $end
$var parameter 32 7 delay $end
$upscope $end
$scope module xor1 $end
$var wire 1 0 a $end
$var wire 1 / b $end
$var wire 1 1 out $end
$var parameter 32 8 delay $end
$upscope $end
$upscope $end
$scope module or1 $end
$var wire 1 4 a $end
$var wire 1 3 b $end
$var wire 1 2 out $end
$var parameter 32 9 delay $end
$upscope $end
$upscope $end
$scope module full_adder1[1] $end
$var wire 1 : a $end
$var wire 1 ; b $end
$var wire 1 < cin $end
$var wire 1 = sum_half $end
$var wire 1 > sum $end
$var wire 1 ? cout $end
$var wire 1 @ carry_half_2 $end
$var wire 1 A carry_half $end
$scope module half_adder1 $end
$var wire 1 : a $end
$var wire 1 ; b $end
$var wire 1 = sum $end
$var wire 1 A carry $end
$scope module and1 $end
$var wire 1 : a $end
$var wire 1 ; b $end
$var wire 1 A out $end
$var parameter 32 B delay $end
$upscope $end
$scope module xor1 $end
$var wire 1 : a $end
$var wire 1 ; b $end
$var wire 1 = out $end
$var parameter 32 C delay $end
$upscope $end
$upscope $end
$scope module half_adder2 $end
$var wire 1 = a $end
$var wire 1 < b $end
$var wire 1 > sum $end
$var wire 1 @ carry $end
$scope module and1 $end
$var wire 1 = a $end
$var wire 1 < b $end
$var wire 1 @ out $end
$var parameter 32 D delay $end
$upscope $end
$scope module xor1 $end
$var wire 1 = a $end
$var wire 1 < b $end
$var wire 1 > out $end
$var parameter 32 E delay $end
$upscope $end
$upscope $end
$scope module or1 $end
$var wire 1 A a $end
$var wire 1 @ b $end
$var wire 1 ? out $end
$var parameter 32 F delay $end
$upscope $end
$upscope $end
$scope module full_adder1[2] $end
$var wire 1 G a $end
$var wire 1 H b $end
$var wire 1 I cin $end
$var wire 1 J sum_half $end
$var wire 1 K sum $end
$var wire 1 L cout $end
$var wire 1 M carry_half_2 $end
$var wire 1 N carry_half $end
$scope module half_adder1 $end
$var wire 1 G a $end
$var wire 1 H b $end
$var wire 1 J sum $end
$var wire 1 N carry $end
$scope module and1 $end
$var wire 1 G a $end
$var wire 1 H b $end
$var wire 1 N out $end
$var parameter 32 O delay $end
$upscope $end
$scope module xor1 $end
$var wire 1 G a $end
$var wire 1 H b $end
$var wire 1 J out $end
$var parameter 32 P delay $end
$upscope $end
$upscope $end
$scope module half_adder2 $end
$var wire 1 J a $end
$var wire 1 I b $end
$var wire 1 K sum $end
$var wire 1 M carry $end
$scope module and1 $end
$var wire 1 J a $end
$var wire 1 I b $end
$var wire 1 M out $end
$var parameter 32 Q delay $end
$upscope $end
$scope module xor1 $end
$var wire 1 J a $end
$var wire 1 I b $end
$var wire 1 K out $end
$var parameter 32 R delay $end
$upscope $end
$upscope $end
$scope module or1 $end
$var wire 1 N a $end
$var wire 1 M b $end
$var wire 1 L out $end
$var parameter 32 S delay $end
$upscope $end
$upscope $end
$scope module full_adder1[3] $end
$var wire 1 T a $end
$var wire 1 U b $end
$var wire 1 V cin $end
$var wire 1 W sum_half $end
$var wire 1 X sum $end
$var wire 1 Y cout $end
$var wire 1 Z carry_half_2 $end
$var wire 1 [ carry_half $end
$scope module half_adder1 $end
$var wire 1 T a $end
$var wire 1 U b $end
$var wire 1 W sum $end
$var wire 1 [ carry $end
$scope module and1 $end
$var wire 1 T a $end
$var wire 1 U b $end
$var wire 1 [ out $end
$var parameter 32 \ delay $end
$upscope $end
$scope module xor1 $end
$var wire 1 T a $end
$var wire 1 U b $end
$var wire 1 W out $end
$var parameter 32 ] delay $end
$upscope $end
$upscope $end
$scope module half_adder2 $end
$var wire 1 W a $end
$var wire 1 V b $end
$var wire 1 X sum $end
$var wire 1 Z carry $end
$scope module and1 $end
$var wire 1 W a $end
$var wire 1 V b $end
$var wire 1 Z out $end
$var parameter 32 ^ delay $end
$upscope $end
$scope module xor1 $end
$var wire 1 W a $end
$var wire 1 V b $end
$var wire 1 X out $end
$var parameter 32 _ delay $end
$upscope $end
$upscope $end
$scope module or1 $end
$var wire 1 [ a $end
$var wire 1 Z b $end
$var wire 1 Y out $end
$var parameter 32 ` delay $end
$upscope $end
$upscope $end
$upscope $end
$upscope $end
$enddefinitions $end
$comment Show the parameter values. $end
$dumpall
b1010 `
b1010 _
b1010 ^
b1010 ]
b1010 \
b1010 S
b1010 R
b1010 Q
b1010 P
b1010 O
b1010 F
b1010 E
b1010 D
b1010 C
b1010 B
b1010 9
b1010 8
b1010 7
b1010 6
b1010 5
b100 ,
b100 $
b11111010000 #
$end
#0
$dumpvars
x[
xZ
xY
xX
xW
xV
0U
0T
xN
xM
xL
xK
xJ
xI
0H
0G
xA
x@
x?
x>
x=
x<
0;
0:
x4
x3
x2
x1
x0
0/
0.
0-
bx +
bx *
b0 )
b0 (
0'
b0 &
b0 %
x"
bx !
$end
#10
03
04
00
0A
0=
0N
0J
0[
0W
#20
0<
bx0 +
02
bx0 !
bx0 *
01
0@
0M
0Z
#30
0I
0V
b0 +
0"
bx00 !
bx00 *
0>
0?
0L
0Y
#40
0K
b0 !
b0 *
0X
#2000
1/
1;
1H
1:
1T
1'
b110 &
b110 )
b1010 %
b1010 (
#2010
b1 !
b1 *
11
1J
1A
1W
#2020
1I
b10 +
1K
1?
b1101 !
b1101 *
1X
#2030
1M
b1001 !
b1001 *
0K
#2040
1V
b110 +
1L
#2050
1Z
b1 !
b1 *
0X
#2060
1"
1Y
#4000
0/
1.
0;
0H
1-
1G
0'
b1 &
b1 )
b1111 %
b1111 (
#4010
b0 !
b0 *
01
0A
1=
14
#4020
1<
0I
b101 +
0?
b10 !
b10 *
1>
12
#4030
1@
0>
0M
b100 !
b100 *
1K
#4040
1I
0V
b11 +
1?
0L
#4050
1M
0K
0Z
b1000 !
b1000 *
1X
#4060
1V
b111 +
0"
1L
0Y
#4070
1Z
b0 !
b0 *
0X
#4080
1"
1Y
#6000
1/
1;
0:
0T
1'
b11 &
b11 )
b101 %
b101 (
#6010
b1 !
b1 *
11
0W
#6020
0Z
b1001 !
b1001 *
1X
#6030
0"
0Y
#8000
0/
0.
1U
0-
1T
0'
b1010 &
b1010 )
b1100 %
b1100 (
#8010
b1000 !
b1000 *
01
04
1[
#8020
0<
b110 +
1"
02
1Y
#8030
0@
b1010 !
b1010 *
1>
#8040
0I
b100 +
0?
#8050
0M
b1110 !
b1110 *
1K
#8060
0V
b0 +
0L
#8070
b110 !
b110 *
0X
#10000
1/
1.
0;
1-
1:
0T
1'
b1001 &
b1001 )
b111 %
b111 (
#10010
b111 !
b111 *
11
14
0[
1W
#10020
1<
b1 +
0"
12
0Y
b1111 !
b1111 *
1X
#10030
1@
b1101 !
b1101 *
0>
#10040
1I
b11 +
1?
#10050
1M
b1001 !
b1001 *
0K
#10060
1V
b111 +
1L
#10070
1Z
b1 !
b1 *
0X
#10080
1"
1Y
