old/lib/checked/DelayNor.v
module DelayNor (input a, b, output out);
	parameter delay = 10;
	nor #delay nor_gate (out, a, b);
endmodule

old/lib/checked/DelayNot.v
module DelayNot (input a ,output out);
	parameter delay = 10;
	not #delay not_gate (out, a);
endmodule

old/lib/checked/falling_edge_detector.v
module falling_edge_detector (input clk, output out);
	wire net1, net2, net3;
	DelayNot not1 (.a(clk), .out(net1));
	DelayNot not2 (.a(net1), .out(net2));
	DelayNot not3 (.a(net2), .out(net3));
	DelayNor nor1 (.a(clk), .b(net3), .out(out));
endmodule

old/lib/checked/DelayAnd.v
module DelayAnd (input a, b, output out);
	parameter delay = 10;
	and #delay and_gate (out, a, b);
endmodule

old/lib/checked/rising_edge_detector.v
module rising_edge_detector (input clk, output out);
	wire net1, net2, net3;
	DelayNot not1 (.a(clk), .out(net1));
	DelayNot not2 (.a(net1), .out(net2));
	DelayNot not3 (.a(net2), .out(net3));
	DelayAnd and1 (.a(clk), .b(net3), .out(out));
endmodule

old/lib/testbench/edge_detector_tb.v
`timescale 1ns/1ns

module	edge_detector_tb;
	
	reg clk;
	wire [1:0] out;

	rising_edge_detector rising_edge_detector1 (clk, out[0]);
	falling_edge_detector falling_edge_detector1 (clk, out[1]);

	initial begin
		$dumpfile("testbench/edge_detector_tb.vcd");
		$dumpvars(0, edge_detector_tb);

		clk = 0;
		#100 clk = 0;

		#5 clk = 1;
		#5 clk = 0;
		#5 clk = 1;
		#5 clk = 0;
		#5 clk = 1;
		#5 clk = 0;

		#50 clk = 1;
		#10 clk = 0;
		#10 clk = 1;
		#10 clk = 0;
		#10 clk = 1;
		#10 clk = 0;

		#50 clk = 0;
		#20 clk = 1;
		#20 clk = 0;
		#20 clk = 1;
		#20 clk = 0;
		#20 clk = 1;
		#20 clk = 0;

		#50 clk = 0;
		#30 clk = 1;
		#30 clk = 0;
		#30 clk = 1;
		#30 clk = 0;
		#30 clk = 1;
		#30 clk = 0;

		#100 clk = 0;
		#40 clk = 1;
		#40 clk = 0;
		#40 clk = 1;
		#40 clk = 0;
		#40 clk = 1;
		#40 clk = 0;

		#200 clk = 0;
		#100 clk = 1;
		#100 clk = 0;
		#100 clk = 1;
		#100 clk = 0;
		#100 clk = 1;
		#100 clk = 0;
		
		#10 $finish;
	end
endmodule

// current directory: 21011056/Q1/lib/
// command: iverilog -o testbench/edge_detector_tb.vvp -s edge_detector_tb -c lib_list.cf testbench/edge_detector_tb.v
// command: vvp testbench/edge_detector_tb.vvp

old/lib/testbench/edge_detector_tb.vcd
$date
	Sun Apr 28 16:50:46 2024
$end
$version
	Icarus Verilog
$end
$timescale
	1ns
$end
$scope module edge_detector_tb $end
$var wire 2 ! out [1:0] $end
$var reg 1 " clk $end
$scope module falling_edge_detector1 $end
$var wire 1 " clk $end
$var wire 1 # out $end
$var wire 1 $ net3 $end
$var wire 1 % net2 $end
$var wire 1 & net1 $end
$scope module nor1 $end
$var wire 1 " a $end
$var wire 1 # out $end
$var wire 1 $ b $end
$var parameter 32 ' delay $end
$upscope $end
$scope module not1 $end
$var wire 1 " a $end
$var wire 1 & out $end
$var parameter 32 ( delay $end
$upscope $end
$scope module not2 $end
$var wire 1 & a $end
$var wire 1 % out $end
$var parameter 32 ) delay $end
$upscope $end
$scope module not3 $end
$var wire 1 % a $end
$var wire 1 $ out $end
$var parameter 32 * delay $end
$upscope $end
$upscope $end
$scope module rising_edge_detector1 $end
$var wire 1 " clk $end
$var wire 1 + out $end
$var wire 1 , net3 $end
$var wire 1 - net2 $end
$var wire 1 . net1 $end
$scope module and1 $end
$var wire 1 " a $end
$var wire 1 + out $end
$var wire 1 , b $end
$var parameter 32 / delay $end
$upscope $end
$scope module not1 $end
$var wire 1 " a $end
$var wire 1 . out $end
$var parameter 32 0 delay $end
$upscope $end
$scope module not2 $end
$var wire 1 . a $end
$var wire 1 - out $end
$var parameter 32 1 delay $end
$upscope $end
$scope module not3 $end
$var wire 1 - a $end
$var wire 1 , out $end
$var parameter 32 2 delay $end
$upscope $end
$upscope $end
$upscope $end
$enddefinitions $end
$comment Show the parameter values. $end
$dumpall
b1010 2
b1010 1
b1010 0
b1010 /
b1010 *
b1010 )
b1010 (
b1010 '
$end
#0
$dumpvars
x.
x-
x,
x+
x&
x%
x$
x#
0"
bx !
$end
#10
1&
1.
bx0 !
0+
#20
0%
0-
#30
1$
1,
#40
b0 !
0#
#105
1"
#110
0"
#115
1"
#120
0"
#125
1"
#130
0"
#180
1"
#190
0&
b1 !
1+
0.
0"
#200
1%
1-
1&
b0 !
0+
1.
1"
#210
0$
0,
0%
0-
0&
b1 !
1+
0.
0"
#220
1$
1,
1%
1-
1#
1&
b10 !
0+
1.
1"
#230
0$
0,
0%
0-
0#
0&
b1 !
1+
0.
0"
#240
1$
1,
1%
1-
1#
1&
b10 !
0+
1.
#250
b0 !
0#
0$
0,
0%
0-
#260
b10 !
1#
1$
1,
#270
b0 !
0#
#300
1"
#310
0&
b1 !
1+
0.
#320
1%
1-
0"
#330
0$
0,
1&
b0 !
0+
1.
#340
b10 !
1#
0%
0-
1"
#350
1$
1,
b0 !
0#
0&
0.
#360
b1 !
1+
1%
1-
0"
#370
0$
0,
1&
b0 !
0+
1.
#380
b10 !
1#
0%
0-
1"
#390
1$
1,
b0 !
0#
0&
0.
#400
b1 !
1+
1%
1-
0"
#410
0$
0,
1&
b0 !
0+
1.
#420
b10 !
1#
0%
0-
#430
1$
1,
#440
b0 !
0#
#480
1"
#490
0&
b1 !
1+
0.
#500
1%
1-
#510
0$
0,
0"
#520
1#
1&
b10 !
0+
1.
#530
0%
0-
#540
1$
1,
1"
#550
0#
0&
b1 !
1+
0.
#560
1%
1-
#570
0$
0,
0"
#580
1#
1&
b10 !
0+
1.
#590
0%
0-
#600
1$
1,
1"
#610
0#
0&
b1 !
1+
0.
#620
1%
1-
#630
0$
0,
0"
#640
1#
1&
b10 !
0+
1.
#650
0%
0-
#660
1$
1,
#670
b0 !
0#
#770
1"
#780
0&
b1 !
1+
0.
#790
1%
1-
#800
0$
0,
#810
b0 !
0+
0"
#820
b10 !
1#
1&
1.
#830
0%
0-
#840
1$
1,
#850
b0 !
0#
1"
#860
0&
b1 !
1+
0.
#870
1%
1-
#880
0$
0,
#890
b0 !
0+
0"
#900
b10 !
1#
1&
1.
#910
0%
0-
#920
1$
1,
#930
b0 !
0#
1"
#940
0&
b1 !
1+
0.
#950
1%
1-
#960
0$
0,
#970
b0 !
0+
0"
#980
b10 !
1#
1&
1.
#990
0%
0-
#1000
1$
1,
#1010
b0 !
0#
#1270
1"
#1280
0&
b1 !
1+
0.
#1290
1%
1-
#1300
0$
0,
#1310
b0 !
0+
#1370
0"
#1380
b10 !
1#
1&
1.
#1390
0%
0-
#1400
1$
1,
#1410
b0 !
0#
#1470
1"
#1480
0&
b1 !
1+
0.
#1490
1%
1-
#1500
0$
0,
#1510
b0 !
0+
#1570
0"
#1580
b10 !
1#
1&
1.
#1590
0%
0-
#1600
1$
1,
#1610
b0 !
0#
#1670
1"
#1680
0&
b1 !
1+
0.
#1690
1%
1-
#1700
0$
0,
#1710
b0 !
0+
#1770
0"
#1780
b10 !
1#
1&
1.
