old/lib/checked/DelayNor.v
module DelayNor (input a, b, output out);
	parameter delay = 10;
	nor #delay nor_gate (out, a, b);
endmodule

old/lib/checked/sr_latch.v
module sr_latch (input s, r, output q, qbar);
	DelayNor nor1 (.a(r), .b(qbar), .out(q));
	DelayNor nor2 (.a(s), .b(q), .out(qbar));
endmodule

old/lib/checked/DelayAnd.v
module DelayAnd (input a, b, output out);
	parameter delay = 10;
	and #delay and_gate (out, a, b);
endmodule

old/lib/checked/DelayNot.v
module DelayNot (input a ,output out);
	parameter delay = 10;
	not #delay not_gate (out, a);
endmodule

old/lib/checked/rising_edge_detector.v
module rising_edge_detector (input clk, output out);
	wire net1, net2, net3;
	DelayNot not1 (.a(clk), .out(net1));
	DelayNot not2 (.a(net1), .out(net2));
	DelayNot not3 (.a(net2), .out(net3));
	DelayAnd and1 (.a(clk), .b(net3), .out(out));
endmodule

old/lib/checked/sr_flip_flop.v
// need to change egde trigger to level trigger
// in order to reduce complexity when using it as an array
// than add edge detector outside of the module

module sr_flip_flop (input s, r, clk, output q, qbar);
	wire en;
	wire net1, net2;
	rising_edge_detector rising_edge_detector1 (.clk(clk), .out(en));
	DelayAnd and1 (.a(s), .b(en), .out(net1));
	DelayAnd and2 (.a(r), .b(en), .out(net2));
	sr_latch sr_latch1 (.s(net1), .r(net2), .q(q), .qbar(qbar));
endmodule

old/lib/checked/d_flip_flop.v
module d_flip_flop (input d, clk, output q, qbar);
	wire dbar;
	DelayNot not1 (.a(d), .out(dbar));
	sr_flip_flop sr_flip_flop1 (.s(d), .r(dbar), .clk(clk), .q(q), .qbar(qbar));
endmodule

old/lib/testbench/flip_flop_tb.v
// Testbench for sr_latch module
`timescale 1ns/1ns

module flip_flop_tb;
	reg s, r, clk;
	wire [2:0] q, qbar;

	parameter delay = 2000;
	parameter clock_half = 1000;

	sr_latch sr_latch1 (.s(s), .r(r), .q(q[0]), .qbar(qbar[0]));
	sr_flip_flop sr_flip_flop1 (.s(s), .r(r), .clk(clk), .q(q[1]), .qbar(qbar[1]));
	d_flip_flop d_flip_flop1 (.d(s), .clk(clk), .q(q[2]), .qbar(qbar[2]));

	initial begin
		$dumpfile("testbench/flip_flop_tb.vcd");
		$dumpvars(0, flip_flop_tb);

		clk = 0; // Initialize clock
		#200;
		// Test case 1: Set S=1, R=0
		s = 1;
		r = 0;
		#delay; // Wait
		// Expected output: Q=1, Qbar=0

		// Test case 2: Set S=0, R=1
		s = 0;
		r = 1;
		#delay; // Wait
		// Expected output: Q=0, Qbar=1

		// Test case 3: Set S=0, R=0
		s = 0;
		r = 0;
		#delay; // Wait
		// Expected output: Q=Q (unchanged)

		// Test case 4: Set S=1, R=1
		s = 1;
		r = 1;
		#delay; // Wait
		// Expected output: Invalid state (Q = 0, Qbar = 0) (both S and R are high)

		// Test case 5: Set S=0, R=0
		s = 0;
		r = 0;
		#delay; // Wait
		// Expected output: Invalid state (both S and R are low)

		// Test case 6: Set S=1, R=0
		s = 1;
		r = 0;
		#delay; // Wait
		// Expected output: Q=1, Qbar=0

		$finish; // End simulation
	end

	always #clock_half clk = ~clk; // Clock toggles every clock_half
endmodule

// current directory: 21011056/Q1/lib/
// command: iverilog -o testbench/flip_flop_tb.vvp -c lib_list.cf testbench/flip_flop_tb.v
// command: vvp testbench/flip_flop_tb.vvp

old/lib/testbench/flip_flop_tb.vcd
$date
	Sun Apr 28 16:59:40 2024
$end
$version
	Icarus Verilog
$end
$timescale
	1ns
$end
$scope module flip_flop_tb $end
$var wire 3 ! qbar [2:0] $end
$var wire 3 " q [2:0] $end
$var parameter 32 # clock_half $end
$var parameter 32 $ delay $end
$var reg 1 % clk $end
$var reg 1 & r $end
$var reg 1 ' s $end
$scope module d_flip_flop1 $end
$var wire 1 % clk $end
$var wire 1 ' d $end
$var wire 1 ( qbar $end
$var wire 1 ) q $end
$var wire 1 * dbar $end
$scope module not1 $end
$var wire 1 ' a $end
$var wire 1 * out $end
$var parameter 32 + delay $end
$upscope $end
$scope module sr_flip_flop1 $end
$var wire 1 % clk $end
$var wire 1 * r $end
$var wire 1 ' s $end
$var wire 1 ( qbar $end
$var wire 1 ) q $end
$var wire 1 , net2 $end
$var wire 1 - net1 $end
$var wire 1 . en $end
$scope module and1 $end
$var wire 1 ' a $end
$var wire 1 - out $end
$var wire 1 . b $end
$var parameter 32 / delay $end
$upscope $end
$scope module and2 $end
$var wire 1 * a $end
$var wire 1 , out $end
$var wire 1 . b $end
$var parameter 32 0 delay $end
$upscope $end
$scope module rising_edge_detector1 $end
$var wire 1 % clk $end
$var wire 1 . out $end
$var wire 1 1 net3 $end
$var wire 1 2 net2 $end
$var wire 1 3 net1 $end
$scope module and1 $end
$var wire 1 % a $end
$var wire 1 . out $end
$var wire 1 1 b $end
$var parameter 32 4 delay $end
$upscope $end
$scope module not1 $end
$var wire 1 % a $end
$var wire 1 3 out $end
$var parameter 32 5 delay $end
$upscope $end
$scope module not2 $end
$var wire 1 3 a $end
$var wire 1 2 out $end
$var parameter 32 6 delay $end
$upscope $end
$scope module not3 $end
$var wire 1 2 a $end
$var wire 1 1 out $end
$var parameter 32 7 delay $end
$upscope $end
$upscope $end
$scope module sr_latch1 $end
$var wire 1 , r $end
$var wire 1 - s $end
$var wire 1 ( qbar $end
$var wire 1 ) q $end
$scope module nor1 $end
$var wire 1 , a $end
$var wire 1 ) out $end
$var wire 1 ( b $end
$var parameter 32 8 delay $end
$upscope $end
$scope module nor2 $end
$var wire 1 - a $end
$var wire 1 ) b $end
$var wire 1 ( out $end
$var parameter 32 9 delay $end
$upscope $end
$upscope $end
$upscope $end
$upscope $end
$scope module sr_flip_flop1 $end
$var wire 1 % clk $end
$var wire 1 & r $end
$var wire 1 ' s $end
$var wire 1 : qbar $end
$var wire 1 ; q $end
$var wire 1 < net2 $end
$var wire 1 = net1 $end
$var wire 1 > en $end
$scope module and1 $end
$var wire 1 ' a $end
$var wire 1 = out $end
$var wire 1 > b $end
$var parameter 32 ? delay $end
$upscope $end
$scope module and2 $end
$var wire 1 & a $end
$var wire 1 < out $end
$var wire 1 > b $end
$var parameter 32 @ delay $end
$upscope $end
$scope module rising_edge_detector1 $end
$var wire 1 % clk $end
$var wire 1 > out $end
$var wire 1 A net3 $end
$var wire 1 B net2 $end
$var wire 1 C net1 $end
$scope module and1 $end
$var wire 1 % a $end
$var wire 1 > out $end
$var wire 1 A b $end
$var parameter 32 D delay $end
$upscope $end
$scope module not1 $end
$var wire 1 % a $end
$var wire 1 C out $end
$var parameter 32 E delay $end
$upscope $end
$scope module not2 $end
$var wire 1 C a $end
$var wire 1 B out $end
$var parameter 32 F delay $end
$upscope $end
$scope module not3 $end
$var wire 1 B a $end
$var wire 1 A out $end
$var parameter 32 G delay $end
$upscope $end
$upscope $end
$scope module sr_latch1 $end
$var wire 1 < r $end
$var wire 1 = s $end
$var wire 1 : qbar $end
$var wire 1 ; q $end
$scope module nor1 $end
$var wire 1 < a $end
$var wire 1 ; out $end
$var wire 1 : b $end
$var parameter 32 H delay $end
$upscope $end
$scope module nor2 $end
$var wire 1 = a $end
$var wire 1 ; b $end
$var wire 1 : out $end
$var parameter 32 I delay $end
$upscope $end
$upscope $end
$upscope $end
$scope module sr_latch1 $end
$var wire 1 & r $end
$var wire 1 ' s $end
$var wire 1 J qbar $end
$var wire 1 K q $end
$scope module nor1 $end
$var wire 1 & a $end
$var wire 1 K out $end
$var wire 1 J b $end
$var parameter 32 L delay $end
$upscope $end
$scope module nor2 $end
$var wire 1 ' a $end
$var wire 1 K b $end
$var wire 1 J out $end
$var parameter 32 M delay $end
$upscope $end
$upscope $end
$upscope $end
$enddefinitions $end
$comment Show the parameter values. $end
$dumpall
b1010 M
b1010 L
b1010 I
b1010 H
b1010 G
b1010 F
b1010 E
b1010 D
b1010 @
b1010 ?
b1010 9
b1010 8
b1010 7
b1010 6
b1010 5
b1010 4
b1010 0
b1010 /
b1010 +
b11111010000 $
b1111101000 #
$end
#0
$dumpvars
xK
xJ
xC
xB
xA
x>
x=
x<
x;
x:
x3
x2
x1
x.
x-
x,
x*
x)
x(
x'
x&
0%
bx "
bx !
$end
#10
13
1C
0>
0.
#20
02
0B
0<
0=
0,
0-
#30
11
1A
#200
0&
1'
#210
0*
bx0 !
0J
#220
bx1 "
1K
#1000
1%
#1010
1.
03
1>
0C
#1020
1-
12
1=
1B
#1030
0(
01
b0 !
0:
0A
#1040
1)
0.
b111 "
1;
0>
#1050
0-
0=
#2000
0%
#2010
13
1C
#2020
02
0B
#2030
11
1A
#2200
1&
0'
#2210
b110 "
0K
1*
#2220
b1 !
1J
#3000
1%
#3010
1.
03
1>
0C
#3020
1,
12
1<
1B
#3030
0)
01
b0 "
0;
0A
#3040
1(
0.
b111 !
1:
0>
#3050
0,
0<
#4000
0%
#4010
13
1C
#4020
02
0B
#4030
11
1A
#4200
0&
#5000
1%
#5010
1.
03
1>
0C
#5020
1,
12
1B
#5030
01
0A
#5040
0.
0>
#5050
0,
#6000
0%
#6010
13
1C
#6020
02
0B
#6030
11
1A
#6200
1&
1'
#6210
0*
b110 !
0J
#7000
1%
#7010
1.
03
1>
0C
#7020
1-
12
1<
1=
1B
#7030
0(
01
b0 !
0:
0A
#7040
b100 "
1)
0.
0>
#7050
0-
0<
0=
#7060
b110 "
1;
b10 !
1:
#7070
b0 !
0:
b100 "
0;
#7080
b110 "
1;
b10 !
1:
#7090
b0 !
0:
b100 "
0;
#7100
b110 "
1;
b10 !
1:
#7110
b0 !
0:
b100 "
0;
#7120
b110 "
1;
b10 !
1:
#7130
b0 !
0:
b100 "
0;
#7140
b110 "
1;
b10 !
1:
#7150
b0 !
0:
b100 "
0;
#7160
b110 "
1;
b10 !
1:
#7170
b0 !
0:
b100 "
0;
#7180
b110 "
1;
b10 !
1:
#7190
b0 !
0:
b100 "
0;
#7200
b110 "
1;
b10 !
1:
#7210
b0 !
0:
b100 "
0;
#7220
b110 "
1;
b10 !
1:
#7230
b0 !
0:
b100 "
0;
#7240
b110 "
1;
b10 !
1:
#7250
b0 !
0:
b100 "
0;
#7260
b110 "
1;
b10 !
1:
#7270
b0 !
0:
b100 "
0;
#7280
b110 "
1;
b10 !
1:
#7290
b0 !
0:
b100 "
0;
#7300
b110 "
1;
b10 !
1:
#7310
b0 !
0:
b100 "
0;
#7320
b110 "
1;
b10 !
1:
#7330
b0 !
0:
b100 "
0;
#7340
b110 "
1;
b10 !
1:
#7350
b0 !
0:
b100 "
0;
#7360
b110 "
1;
b10 !
1:
#7370
b0 !
0:
b100 "
0;
#7380
b110 "
1;
b10 !
1:
#7390
b0 !
0:
b100 "
0;
#7400
b110 "
1;
b10 !
1:
#7410
b0 !
0:
b100 "
0;
#7420
b110 "
1;
b10 !
1:
#7430
b0 !
0:
b100 "
0;
#7440
b110 "
1;
b10 !
1:
#7450
b0 !
0:
b100 "
0;
#7460
b110 "
1;
b10 !
1:
#7470
b0 !
0:
b100 "
0;
#7480
b110 "
1;
b10 !
1:
#7490
b0 !
0:
b100 "
0;
#7500
b110 "
1;
b10 !
1:
#7510
b0 !
0:
b100 "
0;
#7520
b110 "
1;
b10 !
1:
#7530
b0 !
0:
b100 "
0;
#7540
b110 "
1;
b10 !
1:
#7550
b0 !
0:
b100 "
0;
#7560
b110 "
1;
b10 !
1:
#7570
b0 !
0:
b100 "
0;
#7580
b110 "
1;
b10 !
1:
#7590
b0 !
0:
b100 "
0;
#7600
b110 "
1;
b10 !
1:
#7610
b0 !
0:
b100 "
0;
#7620
b110 "
1;
b10 !
1:
#7630
b0 !
0:
b100 "
0;
#7640
b110 "
1;
b10 !
1:
#7650
b0 !
0:
b100 "
0;
#7660
b110 "
1;
b10 !
1:
#7670
b0 !
0:
b100 "
0;
#7680
b110 "
1;
b10 !
1:
#7690
b0 !
0:
b100 "
0;
#7700
b110 "
1;
b10 !
1:
#7710
b0 !
0:
b100 "
0;
#7720
b110 "
1;
b10 !
1:
#7730
b0 !
0:
b100 "
0;
#7740
b110 "
1;
b10 !
1:
#7750
b0 !
0:
b100 "
0;
#7760
b110 "
1;
b10 !
1:
#7770
b0 !
0:
b100 "
0;
#7780
b110 "
1;
b10 !
1:
#7790
b0 !
0:
b100 "
0;
#7800
b110 "
1;
b10 !
1:
#7810
b0 !
0:
b100 "
0;
#7820
b110 "
1;
b10 !
1:
#7830
b0 !
0:
b100 "
0;
#7840
b110 "
1;
b10 !
1:
#7850
b0 !
0:
b100 "
0;
#7860
b110 "
1;
b10 !
1:
#7870
b0 !
0:
b100 "
0;
#7880
b110 "
1;
b10 !
1:
#7890
b0 !
0:
b100 "
0;
#7900
b110 "
1;
b10 !
1:
#7910
b0 !
0:
b100 "
0;
#7920
b110 "
1;
b10 !
1:
#7930
b0 !
0:
b100 "
0;
#7940
b110 "
1;
b10 !
1:
#7950
b0 !
0:
b100 "
0;
#7960
b110 "
1;
b10 !
1:
#7970
b0 !
0:
b100 "
0;
#7980
b110 "
1;
b10 !
1:
#7990
b0 !
0:
b100 "
0;
#8000
b110 "
1;
b10 !
1:
0%
#8010
b0 !
0:
b100 "
0;
13
1C
#8020
b110 "
1;
b10 !
1:
02
0B
#8030
b0 !
0:
b100 "
0;
11
1A
#8040
b110 "
1;
b10 !
1:
#8050
b0 !
0:
b100 "
0;
#8060
b110 "
1;
b10 !
1:
#8070
b0 !
0:
b100 "
0;
#8080
b110 "
1;
b10 !
1:
#8090
b0 !
0:
b100 "
0;
#8100
b110 "
1;
b10 !
1:
#8110
b0 !
0:
b100 "
0;
#8120
b110 "
1;
b10 !
1:
#8130
b0 !
0:
b100 "
0;
#8140
b110 "
1;
b10 !
1:
#8150
b0 !
0:
b100 "
0;
#8160
b110 "
1;
b10 !
1:
#8170
b0 !
0:
b100 "
0;
#8180
b110 "
1;
b10 !
1:
#8190
b0 !
0:
b100 "
0;
#8200
b110 "
1;
b10 !
1:
0&
0'
#8210
0:
0;
b101 "
1K
1*
b1 !
1J
#8220
1;
1:
b10 !
0J
b110 "
0K
#8230
0:
0;
b101 "
1K
b1 !
1J
#8240
1;
1:
b10 !
0J
b110 "
0K
#8250
0:
0;
b101 "
1K
b1 !
1J
#8260
1;
1:
b10 !
0J
b110 "
0K
#8270
0:
0;
b101 "
1K
b1 !
1J
#8280
1;
1:
b10 !
0J
b110 "
0K
#8290
0:
0;
b101 "
1K
b1 !
1J
#8300
1;
1:
b10 !
0J
b110 "
0K
#8310
0:
0;
b101 "
1K
b1 !
1J
#8320
1;
1:
b10 !
0J
b110 "
0K
#8330
0:
0;
b101 "
1K
b1 !
1J
#8340
1;
1:
b10 !
0J
b110 "
0K
#8350
0:
0;
b101 "
1K
b1 !
1J
#8360
1;
1:
b10 !
0J
b110 "
0K
#8370
0:
0;
b101 "
1K
b1 !
1J
#8380
1;
1:
b10 !
0J
b110 "
0K
#8390
0:
0;
b101 "
1K
b1 !
1J
#8400
1;
1:
b10 !
0J
b110 "
0K
#8410
0:
0;
b101 "
1K
b1 !
1J
#8420
1;
1:
b10 !
0J
b110 "
0K
#8430
0:
0;
b101 "
1K
b1 !
1J
#8440
1;
1:
b10 !
0J
b110 "
0K
#8450
0:
0;
b101 "
1K
b1 !
1J
#8460
1;
1:
b10 !
0J
b110 "
0K
#8470
0:
0;
b101 "
1K
b1 !
1J
#8480
1;
1:
b10 !
0J
b110 "
0K
#8490
0:
0;
b101 "
1K
b1 !
1J
#8500
1;
1:
b10 !
0J
b110 "
0K
#8510
0:
0;
b101 "
1K
b1 !
1J
#8520
1;
1:
b10 !
0J
b110 "
0K
#8530
0:
0;
b101 "
1K
b1 !
1J
#8540
1;
1:
b10 !
0J
b110 "
0K
#8550
0:
0;
b101 "
1K
b1 !
1J
#8560
1;
1:
b10 !
0J
b110 "
0K
#8570
0:
0;
b101 "
1K
b1 !
1J
#8580
1;
1:
b10 !
0J
b110 "
0K
#8590
0:
0;
b101 "
1K
b1 !
1J
#8600
1;
1:
b10 !
0J
b110 "
0K
#8610
0:
0;
b101 "
1K
b1 !
1J
#8620
1;
1:
b10 !
0J
b110 "
0K
#8630
0:
0;
b101 "
1K
b1 !
1J
#8640
1;
1:
b10 !
0J
b110 "
0K
#8650
0:
0;
b101 "
1K
b1 !
1J
#8660
1;
1:
b10 !
0J
b110 "
0K
#8670
0:
0;
b101 "
1K
b1 !
1J
#8680
1;
1:
b10 !
0J
b110 "
0K
#8690
0:
0;
b101 "
1K
b1 !
1J
#8700
1;
1:
b10 !
0J
b110 "
0K
#8710
0:
0;
b101 "
1K
b1 !
1J
#8720
1;
1:
b10 !
0J
b110 "
0K
#8730
0:
0;
b101 "
1K
b1 !
1J
#8740
1;
1:
b10 !
0J
b110 "
0K
#8750
0:
0;
b101 "
1K
b1 !
1J
#8760
1;
1:
b10 !
0J
b110 "
0K
#8770
0:
0;
b101 "
1K
b1 !
1J
#8780
1;
1:
b10 !
0J
b110 "
0K
#8790
0:
0;
b101 "
1K
b1 !
1J
#8800
1;
1:
b10 !
0J
b110 "
0K
#8810
0:
0;
b101 "
1K
b1 !
1J
#8820
1;
1:
b10 !
0J
b110 "
0K
#8830
0:
0;
b101 "
1K
b1 !
1J
#8840
1;
1:
b10 !
0J
b110 "
0K
#8850
0:
0;
b101 "
1K
b1 !
1J
#8860
1;
1:
b10 !
0J
b110 "
0K
#8870
0:
0;
b101 "
1K
b1 !
1J
#8880
1;
1:
b10 !
0J
b110 "
0K
#8890
0:
0;
b101 "
1K
b1 !
1J
#8900
1;
1:
b10 !
0J
b110 "
0K
#8910
0:
0;
b101 "
1K
b1 !
1J
#8920
1;
1:
b10 !
0J
b110 "
0K
#8930
0:
0;
b101 "
1K
b1 !
1J
#8940
1;
1:
b10 !
0J
b110 "
0K
#8950
0:
0;
b101 "
1K
b1 !
1J
#8960
1;
1:
b10 !
0J
b110 "
0K
#8970
0:
0;
b101 "
1K
b1 !
1J
#8980
1;
1:
b10 !
0J
b110 "
0K
#8990
0:
0;
b101 "
1K
b1 !
1J
#9000
1;
1:
b10 !
0J
b110 "
0K
1%
#9010
0:
0;
b101 "
1K
b1 !
1J
1.
03
1>
0C
#9020
1;
1:
b10 !
0J
b110 "
0K
1,
12
1B
#9030
0:
0;
1K
b1 !
1J
b1 "
0)
01
0A
#9040
1;
1:
0J
b10 "
0K
b110 !
1(
0.
0>
#9050
0:
0;
b1 "
1K
b101 !
1J
0,
#9060
1;
1:
b110 !
0J
b10 "
0K
#9070
0:
0;
b1 "
1K
b101 !
1J
#9080
1;
1:
b110 !
0J
b10 "
0K
#9090
0:
0;
b1 "
1K
b101 !
1J
#9100
1;
1:
b110 !
0J
b10 "
0K
#9110
0:
0;
b1 "
1K
b101 !
1J
#9120
1;
1:
b110 !
0J
b10 "
0K
#9130
0:
0;
b1 "
1K
b101 !
1J
#9140
1;
1:
b110 !
0J
b10 "
0K
#9150
0:
0;
b1 "
1K
b101 !
1J
#9160
1;
1:
b110 !
0J
b10 "
0K
#9170
0:
0;
b1 "
1K
b101 !
1J
#9180
1;
1:
b110 !
0J
b10 "
0K
#9190
0:
0;
b1 "
1K
b101 !
1J
#9200
1;
1:
b110 !
0J
b10 "
0K
#9210
0:
0;
b1 "
1K
b101 !
1J
#9220
1;
1:
b110 !
0J
b10 "
0K
#9230
0:
0;
b1 "
1K
b101 !
1J
#9240
1;
1:
b110 !
0J
b10 "
0K
#9250
0:
0;
b1 "
1K
b101 !
1J
#9260
1;
1:
b110 !
0J
b10 "
0K
#9270
0:
0;
b1 "
1K
b101 !
1J
#9280
1;
1:
b110 !
0J
b10 "
0K
#9290
0:
0;
b1 "
1K
b101 !
1J
#9300
1;
1:
b110 !
0J
b10 "
0K
#9310
0:
0;
b1 "
1K
b101 !
1J
#9320
1;
1:
b110 !
0J
b10 "
0K
#9330
0:
0;
b1 "
1K
b101 !
1J
#9340
1;
1:
b110 !
0J
b10 "
0K
#9350
0:
0;
b1 "
1K
b101 !
1J
#9360
1;
1:
b110 !
0J
b10 "
0K
#9370
0:
0;
b1 "
1K
b101 !
1J
#9380
1;
1:
b110 !
0J
b10 "
0K
#9390
0:
0;
b1 "
1K
b101 !
1J
#9400
1;
1:
b110 !
0J
b10 "
0K
#9410
0:
0;
b1 "
1K
b101 !
1J
#9420
1;
1:
b110 !
0J
b10 "
0K
#9430
0:
0;
b1 "
1K
b101 !
1J
#9440
1;
1:
b110 !
0J
b10 "
0K
#9450
0:
0;
b1 "
1K
b101 !
1J
#9460
1;
1:
b110 !
0J
b10 "
0K
#9470
0:
0;
b1 "
1K
b101 !
1J
#9480
1;
1:
b110 !
0J
b10 "
0K
#9490
0:
0;
b1 "
1K
b101 !
1J
#9500
1;
1:
b110 !
0J
b10 "
0K
#9510
0:
0;
b1 "
1K
b101 !
1J
#9520
1;
1:
b110 !
0J
b10 "
0K
#9530
0:
0;
b1 "
1K
b101 !
1J
#9540
1;
1:
b110 !
0J
b10 "
0K
#9550
0:
0;
b1 "
1K
b101 !
1J
#9560
1;
1:
b110 !
0J
b10 "
0K
#9570
0:
0;
b1 "
1K
b101 !
1J
#9580
1;
1:
b110 !
0J
b10 "
0K
#9590
0:
0;
b1 "
1K
b101 !
1J
#9600
1;
1:
b110 !
0J
b10 "
0K
#9610
0:
0;
b1 "
1K
b101 !
1J
#9620
1;
1:
b110 !
0J
b10 "
0K
#9630
0:
0;
b1 "
1K
b101 !
1J
#9640
1;
1:
b110 !
0J
b10 "
0K
#9650
0:
0;
b1 "
1K
b101 !
1J
#9660
1;
1:
b110 !
0J
b10 "
0K
#9670
0:
0;
b1 "
1K
b101 !
1J
#9680
1;
1:
b110 !
0J
b10 "
0K
#9690
0:
0;
b1 "
1K
b101 !
1J
#9700
1;
1:
b110 !
0J
b10 "
0K
#9710
0:
0;
b1 "
1K
b101 !
1J
#9720
1;
1:
b110 !
0J
b10 "
0K
#9730
0:
0;
b1 "
1K
b101 !
1J
#9740
1;
1:
b110 !
0J
b10 "
0K
#9750
0:
0;
b1 "
1K
b101 !
1J
#9760
1;
1:
b110 !
0J
b10 "
0K
#9770
0:
0;
b1 "
1K
b101 !
1J
#9780
1;
1:
b110 !
0J
b10 "
0K
#9790
0:
0;
b1 "
1K
b101 !
1J
#9800
1;
1:
b110 !
0J
b10 "
0K
#9810
0:
0;
b1 "
1K
b101 !
1J
#9820
1;
1:
b110 !
0J
b10 "
0K
#9830
0:
0;
b1 "
1K
b101 !
1J
#9840
1;
1:
b110 !
0J
b10 "
0K
#9850
0:
0;
b1 "
1K
b101 !
1J
#9860
1;
1:
b110 !
0J
b10 "
0K
#9870
0:
0;
b1 "
1K
b101 !
1J
#9880
1;
1:
b110 !
0J
b10 "
0K
#9890
0:
0;
b1 "
1K
b101 !
1J
#9900
1;
1:
b110 !
0J
b10 "
0K
#9910
0:
0;
b1 "
1K
b101 !
1J
#9920
1;
1:
b110 !
0J
b10 "
0K
#9930
0:
0;
b1 "
1K
b101 !
1J
#9940
1;
1:
b110 !
0J
b10 "
0K
#9950
0:
0;
b1 "
1K
b101 !
1J
#9960
1;
1:
b110 !
0J
b10 "
0K
#9970
0:
0;
b1 "
1K
b101 !
1J
#9980
1;
1:
b110 !
0J
b10 "
0K
#9990
0:
0;
b1 "
1K
b101 !
1J
#10000
1;
1:
b110 !
0J
b10 "
0K
0%
#10010
0:
0;
b1 "
1K
b101 !
1J
13
1C
#10020
1;
1:
b110 !
0J
b10 "
0K
02
0B
#10030
0:
0;
b1 "
1K
b101 !
1J
11
1A
#10040
1;
1:
b110 !
0J
b10 "
0K
#10050
0:
0;
b1 "
1K
b101 !
1J
#10060
1;
1:
b110 !
0J
b10 "
0K
#10070
0:
0;
b1 "
1K
b101 !
1J
#10080
1;
1:
b110 !
0J
b10 "
0K
#10090
0:
0;
b1 "
1K
b101 !
1J
#10100
1;
1:
b110 !
0J
b10 "
0K
#10110
0:
0;
b1 "
1K
b101 !
1J
#10120
1;
1:
b110 !
0J
b10 "
0K
#10130
0:
0;
b1 "
1K
b101 !
1J
#10140
1;
1:
b110 !
0J
b10 "
0K
#10150
0:
0;
b1 "
1K
b101 !
1J
#10160
1;
1:
b110 !
0J
b10 "
0K
#10170
0:
0;
b1 "
1K
b101 !
1J
#10180
1;
1:
b110 !
0J
b10 "
0K
#10190
0:
0;
b1 "
1K
b101 !
1J
#10200
1;
1:
b110 !
0J
b10 "
0K
1'
#10210
b100 !
0:
0;
b1 "
1K
0*
#10220
b11 "
1;
b110 !
1:
#10230
b100 !
0:
b1 "
0;
#10240
b11 "
1;
b110 !
1:
#10250
b100 !
0:
b1 "
0;
#10260
b11 "
1;
b110 !
1:
#10270
b100 !
0:
b1 "
0;
#10280
b11 "
1;
b110 !
1:
#10290
b100 !
0:
b1 "
0;
#10300
b11 "
1;
b110 !
1:
#10310
b100 !
0:
b1 "
0;
#10320
b11 "
1;
b110 !
1:
#10330
b100 !
0:
b1 "
0;
#10340
b11 "
1;
b110 !
1:
#10350
b100 !
0:
b1 "
0;
#10360
b11 "
1;
b110 !
1:
#10370
b100 !
0:
b1 "
0;
#10380
b11 "
1;
b110 !
1:
#10390
b100 !
0:
b1 "
0;
#10400
b11 "
1;
b110 !
1:
#10410
b100 !
0:
b1 "
0;
#10420
b11 "
1;
b110 !
1:
#10430
b100 !
0:
b1 "
0;
#10440
b11 "
1;
b110 !
1:
#10450
b100 !
0:
b1 "
0;
#10460
b11 "
1;
b110 !
1:
#10470
b100 !
0:
b1 "
0;
#10480
b11 "
1;
b110 !
1:
#10490
b100 !
0:
b1 "
0;
#10500
b11 "
1;
b110 !
1:
#10510
b100 !
0:
b1 "
0;
#10520
b11 "
1;
b110 !
1:
#10530
b100 !
0:
b1 "
0;
#10540
b11 "
1;
b110 !
1:
#10550
b100 !
0:
b1 "
0;
#10560
b11 "
1;
b110 !
1:
#10570
b100 !
0:
b1 "
0;
#10580
b11 "
1;
b110 !
1:
#10590
b100 !
0:
b1 "
0;
#10600
b11 "
1;
b110 !
1:
#10610
b100 !
0:
b1 "
0;
#10620
b11 "
1;
b110 !
1:
#10630
b100 !
0:
b1 "
0;
#10640
b11 "
1;
b110 !
1:
#10650
b100 !
0:
b1 "
0;
#10660
b11 "
1;
b110 !
1:
#10670
b100 !
0:
b1 "
0;
#10680
b11 "
1;
b110 !
1:
#10690
b100 !
0:
b1 "
0;
#10700
b11 "
1;
b110 !
1:
#10710
b100 !
0:
b1 "
0;
#10720
b11 "
1;
b110 !
1:
#10730
b100 !
0:
b1 "
0;
#10740
b11 "
1;
b110 !
1:
#10750
b100 !
0:
b1 "
0;
#10760
b11 "
1;
b110 !
1:
#10770
b100 !
0:
b1 "
0;
#10780
b11 "
1;
b110 !
1:
#10790
b100 !
0:
b1 "
0;
#10800
b11 "
1;
b110 !
1:
#10810
b100 !
0:
b1 "
0;
#10820
b11 "
1;
b110 !
1:
#10830
b100 !
0:
b1 "
0;
#10840
b11 "
1;
b110 !
1:
#10850
b100 !
0:
b1 "
0;
#10860
b11 "
1;
b110 !
1:
#10870
b100 !
0:
b1 "
0;
#10880
b11 "
1;
b110 !
1:
#10890
b100 !
0:
b1 "
0;
#10900
b11 "
1;
b110 !
1:
#10910
b100 !
0:
b1 "
0;
#10920
b11 "
1;
b110 !
1:
#10930
b100 !
0:
b1 "
0;
#10940
b11 "
1;
b110 !
1:
#10950
b100 !
0:
b1 "
0;
#10960
b11 "
1;
b110 !
1:
#10970
b100 !
0:
b1 "
0;
#10980
b11 "
1;
b110 !
1:
#10990
b100 !
0:
b1 "
0;
#11000
b11 "
1;
b110 !
1:
1%
#11010
b100 !
0:
b1 "
0;
1.
03
1>
0C
#11020
b11 "
1;
b110 !
1:
1-
12
1=
1B
#11030
b1 "
0;
0(
01
b0 !
0:
0A
#11040
1)
0.
b111 "
1;
0>
#11050
0-
0=
#12000
0%
#12010
13
1C
#12020
02
0B
#12030
11
1A
