old/lib/checked/n_input_and.v
module n_input_and #(
	parameter N = 1
) (
	input [N-1:0] a,
	output out
);
	supply0 gnd;
	supply1 vdd;
	wire [N-1:0] nmos_line;

	nmos nmos1 [N-1:0] (
		nmos_line, {gnd, nmos_line[N-1:1]}, a
	);

	pmos pmos1 [N-1:0] (
		nmos_line[0], vdd, a
	);

	// inverter
	pmos pmos2 (out, vdd, nmos_line[0]);
	nmos nmos2 (out, gnd, nmos_line[0]);

endmodule

old/lib/testbench/n_input_and_tb.v
`timescale 1ns / 1ns

module n_input_and_tb;

	// Parameters
	parameter N = 4;
	parameter DELAY = 200;

	// Inputs
	reg [N-1:0] a;
	
	// Outputs
	wire out;

	// Instantiate the module under test
	n_input_and #(.N(N)) dut (
		.a(a),
		.out(out)
	);

	// Stimulus
	integer i;
	initial begin
		// Dump VCD file
		$dumpfile("testbench/n_input_and_tb.vcd");
		$dumpvars(0, n_input_and_tb);

		#DELAY;
		// Test Loop
		for (i = 0; i < 2 ** N; i = i + 1) begin
			a = i;
			#DELAY;
		end

		$finish;
	end

endmodule

// current directory: 21011056/Q1/lib
// command: iverilog -o testbench/n_input_and_tb.vvp -y ../lib testbench/n_input_and_tb.v
// command: vvp testbench/n_input_and_tb.vvp

old/lib/testbench/n_input_and_tb.vcd
$date
	Tue Apr 30 00:15:53 2024
$end
$version
	Icarus Verilog
$end
$timescale
	1ns
$end
$scope module n_input_and_tb $end
$var wire 1 ! out $end
$var parameter 32 " DELAY $end
$var parameter 32 # N $end
$var reg 4 $ a [3:0] $end
$var integer 32 % i [31:0] $end
$scope module dut $end
$var wire 4 & a [3:0] $end
$var wire 1 ' gnd $end
$var wire 4 ( nmos_line [3:0] $end
$var wire 1 ! out $end
$var wire 1 ) vdd $end
$var parameter 32 * N $end
$upscope $end
$upscope $end
$enddefinitions $end
$comment Show the parameter values. $end
$dumpall
b100 *
b100 #
b11001000 "
$end
#0
$dumpvars
1)
bx (
0'
bx &
bx %
bx $
x!
$end
#200
0!
bz1 (
b0 $
b0 &
b0 %
#400
b1 $
b1 &
b1 %
#600
b10 $
b10 &
b10 %
#800
b11 $
b11 &
b11 %
#1000
b100 $
b100 &
b100 %
#1200
b101 $
b101 &
b101 %
#1400
b110 $
b110 &
b110 %
#1600
b111 $
b111 &
b111 %
#1800
b0zz1 (
b1000 $
b1000 &
b1000 %
#2000
b1001 $
b1001 &
b1001 %
#2200
b1010 $
b1010 &
b1010 %
#2400
b1011 $
b1011 &
b1011 %
#2600
b0z1 (
b1100 $
b1100 &
b1100 %
#2800
b1101 $
b1101 &
b1101 %
#3000
b1 (
b1110 $
b1110 &
b1110 %
#3200
1!
b0 (
b1111 $
b1111 &
b1111 %
#3400
b10000 %
