old/lib/checked/n_input_or.v
module n_input_or #(parameter N = 2) (input [N-1:0] a, output out);
	//assign out = |a;
	wire [N-1:0] pmos_line;
	supply1 vdd;
	supply0 gnd;
	
	pmos pmos1 (pmos_line[N-1], vdd, a[N-1]);
	pmos pmos2 [N-2:0] (pmos_line[N-2:0], pmos_line[N-1:1], a[N-2:0]);

	nmos nmos1 [N-1:0] (pmos_line[0], gnd, a);

	pmos pmos3 (out, vdd, pmos_line[0]);
	nmos nmos2 (out, gnd, pmos_line[0]);
endmodule

old/lib/testbench/n_input_or_tb.v
module n_input_or_tb;
	reg [31:0] a;
	wire out;
	
	n_input_or #(.N(32)) n_input_or_inst (.a(a), .out(out));
	
	integer i;

	initial begin
		$dumpfile("testbench/n_input_or_tb.vcd");
		$dumpvars(0, n_input_or_tb);

		for (i = 0; i < 2 ** 7; i = i + 1) begin
			a = i;
			#10;
		end

		a = 0;
		#10;
		$finish;
	end

endmodule

// current directory: 21011056/Q1/lib
// command: iverilog -o testbench/n_input_or_tb.vvp -y ../lib testbench/n_input_or_tb.v
// command: vvp testbench/n_input_or_tb.vvp

old/lib/testbench/n_input_or_tb.vcd
$date
	Sun Apr 28 23:58:33 2024
$end
$version
	Icarus Verilog
$end
$timescale
	1s
$end
$scope module n_input_or_tb $end
$var wire 1 ! out $end
$var reg 32 " a [31:0] $end
$var integer 32 # i [31:0] $end
$scope module n_input_or_inst $end
$var wire 32 $ a [31:0] $end
$var wire 1 % gnd $end
$var wire 1 ! out $end
$var wire 32 & pmos_line [31:0] $end
$var wire 1 ' vdd $end
$var parameter 32 ( N $end
$upscope $end
$upscope $end
$enddefinitions $end
$comment Show the parameter values. $end
$dumpall
b100000 (
$end
#0
$dumpvars
1'
b11111111111111111111111111111111 &
0%
b0 $
b0 #
b0 "
0!
$end
#10
1!
b11111111111111111111111111111110 &
b1 "
b1 $
b1 #
#20
1!
b111111111111111111111111111111z0 &
b10 "
b10 $
b10 #
#30
b11 "
b11 $
b11 #
#40
1!
b11111111111111111111111111111zz0 &
b100 "
b100 $
b100 #
#50
b101 "
b101 $
b101 #
#60
b110 "
b110 $
b110 #
#70
b111 "
b111 $
b111 #
#80
1!
b1111111111111111111111111111zzz0 &
b1000 "
b1000 $
b1000 #
#90
b1001 "
b1001 $
b1001 #
#100
b1010 "
b1010 $
b1010 #
#110
b1011 "
b1011 $
b1011 #
#120
b1100 "
b1100 $
b1100 #
#130
b1101 "
b1101 $
b1101 #
#140
b1110 "
b1110 $
b1110 #
#150
b1111 "
b1111 $
b1111 #
#160
1!
b111111111111111111111111111zzzz0 &
b10000 "
b10000 $
b10000 #
#170
b10001 "
b10001 $
b10001 #
#180
b10010 "
b10010 $
b10010 #
#190
b10011 "
b10011 $
b10011 #
#200
b10100 "
b10100 $
b10100 #
#210
b10101 "
b10101 $
b10101 #
#220
b10110 "
b10110 $
b10110 #
#230
b10111 "
b10111 $
b10111 #
#240
b11000 "
b11000 $
b11000 #
#250
b11001 "
b11001 $
b11001 #
#260
b11010 "
b11010 $
b11010 #
#270
b11011 "
b11011 $
b11011 #
#280
b11100 "
b11100 $
b11100 #
#290
b11101 "
b11101 $
b11101 #
#300
b11110 "
b11110 $
b11110 #
#310
b11111 "
b11111 $
b11111 #
#320
1!
b11111111111111111111111111zzzzz0 &
b100000 "
b100000 $
b100000 #
#330
b100001 "
b100001 $
b100001 #
#340
b100010 "
b100010 $
b100010 #
#350
b100011 "
b100011 $
b100011 #
#360
b100100 "
b100100 $
b100100 #
#370
b100101 "
b100101 $
b100101 #
#380
b100110 "
b100110 $
b100110 #
#390
b100111 "
b100111 $
b100111 #
#400
b101000 "
b101000 $
b101000 #
#410
b101001 "
b101001 $
b101001 #
#420
b101010 "
b101010 $
b101010 #
#430
b101011 "
b101011 $
b101011 #
#440
b101100 "
b101100 $
b101100 #
#450
b101101 "
b101101 $
b101101 #
#460
b101110 "
b101110 $
b101110 #
#470
b101111 "
b101111 $
b101111 #
#480
b110000 "
b110000 $
b110000 #
#490
b110001 "
b110001 $
b110001 #
#500
b110010 "
b110010 $
b110010 #
#510
b110011 "
b110011 $
b110011 #
#520
b110100 "
b110100 $
b110100 #
#530
b110101 "
b110101 $
b110101 #
#540
b110110 "
b110110 $
b110110 #
#550
b110111 "
b110111 $
b110111 #
#560
b111000 "
b111000 $
b111000 #
#570
b111001 "
b111001 $
b111001 #
#580
b111010 "
b111010 $
b111010 #
#590
b111011 "
b111011 $
b111011 #
#600
b111100 "
b111100 $
b111100 #
#610
b111101 "
b111101 $
b111101 #
#620
b111110 "
b111110 $
b111110 #
#630
b111111 "
b111111 $
b111111 #
#640
1!
b1111111111111111111111111zzzzzz0 &
b1000000 "
b1000000 $
b1000000 #
#650
b1000001 "
b1000001 $
b1000001 #
#660
b1000010 "
b1000010 $
b1000010 #
#670
b1000011 "
b1000011 $
b1000011 #
#680
b1000100 "
b1000100 $
b1000100 #
#690
b1000101 "
b1000101 $
b1000101 #
#700
b1000110 "
b1000110 $
b1000110 #
#710
b1000111 "
b1000111 $
b1000111 #
#720
b1001000 "
b1001000 $
b1001000 #
#730
b1001001 "
b1001001 $
b1001001 #
#740
b1001010 "
b1001010 $
b1001010 #
#750
b1001011 "
b1001011 $
b1001011 #
#760
b1001100 "
b1001100 $
b1001100 #
#770
b1001101 "
b1001101 $
b1001101 #
#780
b1001110 "
b1001110 $
b1001110 #
#790
b1001111 "
b1001111 $
b1001111 #
#800
b1010000 "
b1010000 $
b1010000 #
#810
b1010001 "
b1010001 $
b1010001 #
#820
b1010010 "
b1010010 $
b1010010 #
#830
b1010011 "
b1010011 $
b1010011 #
#840
b1010100 "
b1010100 $
b1010100 #
#850
b1010101 "
b1010101 $
b1010101 #
#860
b1010110 "
b1010110 $
b1010110 #
#870
b1010111 "
b1010111 $
b1010111 #
#880
b1011000 "
b1011000 $
b1011000 #
#890
b1011001 "
b1011001 $
b1011001 #
#900
b1011010 "
b1011010 $
b1011010 #
#910
b1011011 "
b1011011 $
b1011011 #
#920
b1011100 "
b1011100 $
b1011100 #
#930
b1011101 "
b1011101 $
b1011101 #
#940
b1011110 "
b1011110 $
b1011110 #
#950
b1011111 "
b1011111 $
b1011111 #
#960
b1100000 "
b1100000 $
b1100000 #
#970
b1100001 "
b1100001 $
b1100001 #
#980
b1100010 "
b1100010 $
b1100010 #
#990
b1100011 "
b1100011 $
b1100011 #
#1000
b1100100 "
b1100100 $
b1100100 #
#1010
b1100101 "
b1100101 $
b1100101 #
#1020
b1100110 "
b1100110 $
b1100110 #
#1030
b1100111 "
b1100111 $
b1100111 #
#1040
b1101000 "
b1101000 $
b1101000 #
#1050
b1101001 "
b1101001 $
b1101001 #
#1060
b1101010 "
b1101010 $
b1101010 #
#1070
b1101011 "
b1101011 $
b1101011 #
#1080
b1101100 "
b1101100 $
b1101100 #
#1090
b1101101 "
b1101101 $
b1101101 #
#1100
b1101110 "
b1101110 $
b1101110 #
#1110
b1101111 "
b1101111 $
b1101111 #
#1120
b1110000 "
b1110000 $
b1110000 #
#1130
b1110001 "
b1110001 $
b1110001 #
#1140
b1110010 "
b1110010 $
b1110010 #
#1150
b1110011 "
b1110011 $
b1110011 #
#1160
b1110100 "
b1110100 $
b1110100 #
#1170
b1110101 "
b1110101 $
b1110101 #
#1180
b1110110 "
b1110110 $
b1110110 #
#1190
b1110111 "
b1110111 $
b1110111 #
#1200
b1111000 "
b1111000 $
b1111000 #
#1210
b1111001 "
b1111001 $
b1111001 #
#1220
b1111010 "
b1111010 $
b1111010 #
#1230
b1111011 "
b1111011 $
b1111011 #
#1240
b1111100 "
b1111100 $
b1111100 #
#1250
b1111101 "
b1111101 $
b1111101 #
#1260
b1111110 "
b1111110 $
b1111110 #
#1270
b1111111 "
b1111111 $
b1111111 #
#1280
0!
b11111111111111111111111111111111 &
b0 "
b0 $
b10000000 #
