old/lib/checked/DelayBufIf1.v
module DelayBufIf1 (input a, en, output out);
	parameter delay = 10;
	bufif1 #delay bufif1_gate (out, a, en);
endmodule

old/lib/checked/DelayBuf.v
module DelayBuf (input a, output out);
	parameter delay = 10;
	buf #delay buf_gate (out, a);
endmodule

old/lib/checked/DelayNot.v
module DelayNot (input a ,output out);
	parameter delay = 10;
	not #delay not_gate (out, a);
endmodule

old/lib/checked/DelayXnor.v
module DelayXnor (input a, b, output out);
	parameter delay = 10;
	xnor #delay xnor_gate (out, a, b);
endmodule

old/lib/checked/DelayXor.v
module DelayXor (input a, b, output out);
	parameter delay = 10;
	xor #delay xor_gate (out, a, b);
endmodule

old/lib/checked/DelayNor.v
module DelayNor (input a, b, output out);
	parameter delay = 10;
	nor #delay nor_gate (out, a, b);
endmodule

old/lib/checked/DelayNand.v
module DelayNand (input a, b, output out);
	parameter delay = 10;
	nand #delay nand_gate (out, a, b);
endmodule

old/lib/checked/DelayOr.v
module DelayOr (input a, b, output out);
	parameter delay = 10;
	or #delay or_gate (out, a, b);
endmodule

old/lib/checked/DelayAnd.v
module DelayAnd (input a, b, output out);
	parameter delay = 10;
	and #delay and_gate (out, a, b);
endmodule

old/lib/testbench/primitive_gates_tb.v
`timescale 1ns/1ns

module primitive_gates_tb;
	reg a, b;
	wire [8:0]out;

	DelayAnd and_gate (a, b, out[0]);
	DelayOr or_gate (a, b, out[1]);
	DelayNand nand_gate (a, b, out[2]);
	DelayNor nor_gate (a, b, out[3]);
	DelayXor xor_gate (a, b, out[4]);
	DelayXnor xnor_gate (a, b, out[5]);
	DelayNot not_gate (a, out[6]);
	DelayBuf buf_gate (a, out[7]);
	DelayBufIf1 bufif1_gate (a, b, out[8]);

	initial begin
		$dumpfile("testbench/primitive_gates_tb.vcd");
		$dumpvars(0, primitive_gates_tb);
		a = 0; b = 0;
		#20 a = 0; b = 1;
		#20 a = 1; b = 0;
		#20 a = 1; b = 1;
		#20 $finish;
	end
endmodule

// current directory: 21011056/Q1/lib/
// command: iverilog -o testbench/primitive_gates_tb.vvp primitive_gates.v testbench/primitive_gates_tb.v
// command: vvp testbench/primitive_gates_tb.vvp

old/lib/testbench/primitive_gates_tb.vcd
$date
	Sun Apr 28 02:07:18 2024
$end
$version
	Icarus Verilog
$end
$timescale
	1ns
$end
$scope module primitive_gates_tb $end
$var wire 9 ! out [8:0] $end
$var reg 1 " a $end
$var reg 1 # b $end
$scope module and_gate $end
$var wire 1 " a $end
$var wire 1 # b $end
$var wire 1 $ out $end
$var parameter 32 % delay $end
$upscope $end
$scope module buf_gate $end
$var wire 1 " a $end
$var wire 1 & out $end
$var parameter 32 ' delay $end
$upscope $end
$scope module bufif1_gate $end
$var wire 1 " a $end
$var wire 1 # en $end
$var wire 1 ( out $end
$var parameter 32 ) delay $end
$upscope $end
$scope module nand_gate $end
$var wire 1 " a $end
$var wire 1 # b $end
$var wire 1 * out $end
$var parameter 32 + delay $end
$upscope $end
$scope module nor_gate $end
$var wire 1 " a $end
$var wire 1 # b $end
$var wire 1 , out $end
$var parameter 32 - delay $end
$upscope $end
$scope module not_gate $end
$var wire 1 " a $end
$var wire 1 . out $end
$var parameter 32 / delay $end
$upscope $end
$scope module or_gate $end
$var wire 1 " a $end
$var wire 1 # b $end
$var wire 1 0 out $end
$var parameter 32 1 delay $end
$upscope $end
$scope module xnor_gate $end
$var wire 1 " a $end
$var wire 1 # b $end
$var wire 1 2 out $end
$var parameter 32 3 delay $end
$upscope $end
$scope module xor_gate $end
$var wire 1 " a $end
$var wire 1 # b $end
$var wire 1 4 out $end
$var parameter 32 5 delay $end
$upscope $end
$upscope $end
$enddefinitions $end
$comment Show the parameter values. $end
$dumpall
b1010 5
b1010 3
b1010 1
b1010 /
b1010 -
b1010 +
b1010 )
b1010 '
b1010 %
$end
#0
$dumpvars
x4
x2
x0
x.
x,
x*
x(
x&
x$
0#
0"
bx !
$end
#10
0&
1.
04
12
00
1,
1*
0$
bz01101100 !
z(
#20
1#
#30
0,
10
02
14
b1010110 !
0(
#40
0#
1"
#50
1&
0.
bz10010110 !
z(
#60
1#
#70
1$
0*
12
04
b110100011 !
1(
